{"cameraMode":{"drawMode":0,"name":"Shaded","section":"Shading Mode"},"sceneLighting":true,"audioPlay":false,"sceneViewState":{"m_AlwaysRefresh":false,"showFog":true,"showSkybox":true,"showFlares":true,"showImageEffects":true,"showParticleSystems":true,"showVisualEffectGraphs":true,"m_FxEnabled":true},"in2DMode":false,"pivot":{"x":-10.964509010314942,"y":20.796035766601564,"z":11.958827018737793},"rotation":{"x":0.3479348123073578,"y":0.5989499092102051,"z":-0.3232377767562866,"w":0.6449165940284729},"size":2.3115949630737306,"orthographic":false}